puff.py
setup.cfg
setup.py
puff.egg-info/PKG-INFO
puff.egg-info/SOURCES.txt
puff.egg-info/dependency_links.txt
puff.egg-info/requires.txt
puff.egg-info/top_level.txt