Metadata-Version: 1.1
Name: puff
Version: 0.5
Summary: API Validation for SQLAlchemy-jsonapi
Home-page: https://github.com/rockstar/puff
Author: Paul Hummer
Author-email: paul@eventuallyanyway.com
License: MIT
Platform: UNKNOWN
Classifier: Intended Audience :: Developers
Classifier: Programming Language :: Python
